<annotation>
	<folder>name</folder>
	<filename>name.2b9aaa40-df18-11eb-a3f2-8c47be4b3dc0.jpg</filename>
	<path>D:\Hand-Sign-Prediction-with-Tensorflow-Object-Detection\Tensorflow\workspace\images\collectedimages\name\name.2b9aaa40-df18-11eb-a3f2-8c47be4b3dc0.jpg</path>
	<source>
		<database>Unknown</database>
	</source>
	<size>
		<width>640</width>
		<height>480</height>
		<depth>3</depth>
	</size>
	<segmented>0</segmented>
	<object>
		<name>Name</name>
		<pose>Unspecified</pose>
		<truncated>0</truncated>
		<difficult>0</difficult>
		<bndbox>
			<xmin>402</xmin>
			<ymin>101</ymin>
			<xmax>511</xmax>
			<ymax>173</ymax>
		</bndbox>
	</object>
</annotation>
